{"trial_id": "1b69c35e6c37a5ae9f5775c1ee638356", "hyperparameters": {"space": [{"class_name": "Int", "config": {"name": "units_1", "default": 7, "min_value": 1, "max_value": 10, "step": 1, "sampling": null}}, {"class_name": "Int", "config": {"name": "units_2", "default": 3, "min_value": 0, "max_value": 10, "step": 1, "sampling": null}}, {"class_name": "Choice", "config": {"name": "learning_rate", "default": 0.01, "values": [0.1, 0.01, 0.001, 0.0001, 1e-05], "ordered": true}}, {"class_name": "Choice", "config": {"name": "Activation_function", "default": "relu", "values": ["relu", "sigmoid"], "ordered": false}}], "values": {"units_1": 1, "units_2": 7, "learning_rate": 0.1, "Activation_function": "relu"}}, "metrics": {"metrics": {"loss": {"direction": "min", "observations": [{"value": [0.020778697426445603], "step": 0}]}, "mse": {"direction": "min", "observations": [{"value": [0.02077869512140751], "step": 0}]}, "val_loss": {"direction": "min", "observations": [{"value": [0.0017003401409817376], "step": 0}]}, "val_mse": {"direction": "min", "observations": [{"value": [0.0017003403045237064], "step": 0}]}}}, "score": 0.02077869512140751, "best_step": 0, "status": "COMPLETED"}