{"trial_id": "08d5497fe1f8278480eaae1efee71f21", "hyperparameters": {"space": [{"class_name": "Int", "config": {"name": "units_1", "default": null, "min_value": 10, "max_value": 50, "step": 2, "sampling": null}}, {"class_name": "Int", "config": {"name": "units_2", "default": null, "min_value": 0, "max_value": 50, "step": 2, "sampling": null}}, {"class_name": "Choice", "config": {"name": "learning_rate", "default": 0.001, "values": [0.1, 0.01, 0.001, 0.0001, 1e-05], "ordered": true}}, {"class_name": "Choice", "config": {"name": "Activation_function", "default": "relu", "values": ["relu", "tanh", "sigmoid"], "ordered": false}}], "values": {"units_1": 50, "units_2": 0, "learning_rate": 0.1, "Activation_function": "sigmoid"}}, "metrics": {"metrics": {"loss": {"direction": "min", "observations": [{"value": [0.04236550987836012], "step": 0}]}, "mse": {"direction": "min", "observations": [{"value": [0.042365506291389465], "step": 0}]}, "val_loss": {"direction": "min", "observations": [{"value": [0.012355025680292219], "step": 0}]}, "val_mse": {"direction": "min", "observations": [{"value": [0.012355025857686996], "step": 0}]}}}, "score": 0.042365506291389465, "best_step": 0, "status": "COMPLETED"}